odoo/addons/l10n_cl_currency_rate_sbif/README.rst
odoo/addons/l10n_cl_currency_rate_sbif/__init__.py
odoo/addons/l10n_cl_currency_rate_sbif/__manifest__.py
odoo/addons/l10n_cl_currency_rate_sbif/data/decimal_precision.xml
odoo/addons/l10n_cl_currency_rate_sbif/data/ir_config_parameter.xml
odoo/addons/l10n_cl_currency_rate_sbif/data/ir_cron.xml
odoo/addons/l10n_cl_currency_rate_sbif/data/res.currency.csv
odoo/addons/l10n_cl_currency_rate_sbif/i18n/es_CL.po
odoo/addons/l10n_cl_currency_rate_sbif/i18n/l10n_cl_currency_rate_sbif.pot
odoo/addons/l10n_cl_currency_rate_sbif/models/__init__.py
odoo/addons/l10n_cl_currency_rate_sbif/models/res_currency.py
odoo/addons/l10n_cl_currency_rate_sbif/models/res_currency_rate.py
odoo/addons/l10n_cl_currency_rate_sbif/readme/CONFIGURE.rst
odoo/addons/l10n_cl_currency_rate_sbif/readme/CONTRIBUTORS.rst
odoo/addons/l10n_cl_currency_rate_sbif/readme/DESCRIPTION.rst
odoo/addons/l10n_cl_currency_rate_sbif/readme/HISTORY.rst
odoo/addons/l10n_cl_currency_rate_sbif/readme/INSTALL.rst
odoo/addons/l10n_cl_currency_rate_sbif/readme/ROADMAP.rst
odoo/addons/l10n_cl_currency_rate_sbif/readme/USAGE.rst
odoo/addons/l10n_cl_currency_rate_sbif/static/description/icon.png
odoo/addons/l10n_cl_currency_rate_sbif/static/description/index.html
odoo/addons/l10n_cl_currency_rate_sbif/views/update_button.xml
odoo12_addon_l10n_cl_currency_rate_sbif-12.0.2.0.0.99.dev8.dist-info/METADATA
odoo12_addon_l10n_cl_currency_rate_sbif-12.0.2.0.0.99.dev8.dist-info/WHEEL
odoo12_addon_l10n_cl_currency_rate_sbif-12.0.2.0.0.99.dev8.dist-info/top_level.txt
odoo12_addon_l10n_cl_currency_rate_sbif-12.0.2.0.0.99.dev8.dist-info/RECORD
