Metadata-Version: 2.1
Name: odoo12-addon-l10n-cl-currency-rate-sbif
Version: 12.0.2.0.0.99.dev8
Summary: Update UF, UTM and US Dollar exchange rates using SBIF
Home-page: https://github.com/OCA/l10n-chile
Author: Blanco Martin & Asociados, Konos, Open Source Integrators, Odoo Community Association (OCA)
Author-email: support@odoo-community.org
License: AGPL-3
Platform: UNKNOWN
Classifier: Programming Language :: Python
Classifier: Framework :: Odoo
Classifier: Framework :: Odoo :: 12.0
Classifier: License :: OSI Approved :: GNU Affero General Public License v3
Classifier: Development Status :: 4 - Beta
Requires-Python: >=3.5
Requires-Dist: odoo <12.1dev,>=12.0a
